LICENSE
MANIFEST.in
README.md
pyproject.toml
setup.cfg
setup.py
src/usd2gltf/__init__.py
src/usd2gltf/cli.py
src/usd2gltf/common.py
src/usd2gltf/converter.py
src/usd2gltf.egg-info/PKG-INFO
src/usd2gltf.egg-info/SOURCES.txt
src/usd2gltf.egg-info/dependency_links.txt
src/usd2gltf.egg-info/entry_points.txt
src/usd2gltf.egg-info/requires.txt
src/usd2gltf.egg-info/top_level.txt
src/usd2gltf/converters/__init__.py
src/usd2gltf/converters/usd_camera.py
src/usd2gltf/converters/usd_lux.py
src/usd2gltf/converters/usd_material.py
src/usd2gltf/converters/usd_mesh.py
src/usd2gltf/converters/usd_skel.py
src/usd2gltf/converters/usd_xform.py
tests/test_converter.py