Metadata-Version: 2.1
Name: usd2gltf
Version: 0.3.5
Summary: Convert USD to GLTF
Home-page: https://github.com/mikelyndon/usd2gltf
Author: Mike Lyndon
Author-email: work.mike@pm.me
License: UNKNOWN
Platform: UNKNOWN
Classifier: Programming Language :: Python :: 3
Classifier: License :: OSI Approved :: MIT License
Classifier: Operating System :: OS Independent
Requires-Python: >=3.9
License-File: LICENSE
